pyproject_pipenv/__init__.py
pyproject_pipenv/__main__.py
pyproject_pipenv/converter.py
pyproject_pipenv/models.py
pyproject_pipenv-1.2.0.dist-info/licenses/LICENSE
pyproject_pipenv-1.2.0.dist-info/METADATA
pyproject_pipenv-1.2.0.dist-info/WHEEL
pyproject_pipenv-1.2.0.dist-info/entry_points.txt
pyproject_pipenv-1.2.0.dist-info/top_level.txt
pyproject_pipenv-1.2.0.dist-info/RECORD
