Metadata-Version: 2.4
Name: pyproject-pipenv
Version: 1.2.0
Summary: Sync requirements from Pipfile to pyproject.toml
Author-email: Filipe Pina <shelf-corncob-said@duck.com>
Project-URL: Homepage, https://github.com/fopina/pyproject-pipenv
Classifier: Development Status :: 5 - Production/Stable
Classifier: Intended Audience :: Developers
Classifier: License :: OSI Approved :: BSD License
Classifier: Operating System :: OS Independent
Classifier: Programming Language :: Python
Classifier: Programming Language :: Python :: 3
Classifier: Programming Language :: Python :: 3 :: Only
Classifier: Programming Language :: Python :: 3.9
Classifier: Programming Language :: Python :: 3.10
Classifier: Programming Language :: Python :: 3.11
Classifier: Programming Language :: Python :: 3.12
Requires-Python: <4,>=3.9
License-File: LICENSE
Requires-Dist: tomlkit<1.0.0
Dynamic: license-file
